jupyter_sphinx/__init__.py
jupyter_sphinx/_version.py
jupyter_sphinx/ast.py
jupyter_sphinx/execute.py
jupyter_sphinx/thebelab.py
jupyter_sphinx/utils.py
jupyter_sphinx/css/jupyter-sphinx.css
jupyter_sphinx/thebelab/thebelab-helper.js
jupyter_sphinx/thebelab/thebelab.css
jupyter_sphinx-0.3.2.dist-info/LICENSE
jupyter_sphinx-0.3.2.dist-info/METADATA
jupyter_sphinx-0.3.2.dist-info/WHEEL
jupyter_sphinx-0.3.2.dist-info/top_level.txt
jupyter_sphinx-0.3.2.dist-info/RECORD
